README.md
setup.py
sample/__init__.py
sample/hello_world.py
sample_1_2023.egg-info/PKG-INFO
sample_1_2023.egg-info/SOURCES.txt
sample_1_2023.egg-info/dependency_links.txt
sample_1_2023.egg-info/requires.txt
sample_1_2023.egg-info/top_level.txt