Metadata-Version: 2.1
Name: sample-1-2023
Version: 0.0.5
Summary: A user-friendly wrapper for the Kite Connect library
Home-page: https://github.com/AST-LW/kite_connect_lite
